Metadata-Version: 1.1
Name: marsi
Version: 0.3.5
Summary: marsi - Metabolite Analogues for Rational Strain Improvement
Home-page: https://github.com/biosustain/marsi
Author: Joao Cardoso
Author-email: joaca@biosustain.dtu.dk
License: Apache License Version 2.0
Keywords: biology metabolism bioinformatics chemoinformatics
Platform: UNKNOWN
Classifier: Development Status :: 3 - Alpha
Classifier: Programming Language :: Python :: 3.5
Classifier: Programming Language :: Python :: 2.7
Classifier: License :: OSI Approved :: Apache Software License
Classifier: Topic :: Scientific/Engineering :: Bio-Informatics
